AUTHORS
LICENSE
MANIFEST.in
README.rst
setup.py
django_eldarion_ajax.egg-info/PKG-INFO
django_eldarion_ajax.egg-info/SOURCES.txt
django_eldarion_ajax.egg-info/dependency_links.txt
django_eldarion_ajax.egg-info/not-zip-safe
django_eldarion_ajax.egg-info/top_level.txt
eldarion/__init__.py
eldarion/ajax/__init__.py
eldarion/ajax/views.py
eldarion/ajax/tests/__init__.py
eldarion/ajax/tests/models.py
eldarion/ajax/tests/tests.py
eldarion/ajax/tests/urls.py