Metadata-Version: 1.1
Name: django-eldarion-ajax
Version: 0.1
Summary: a companion app to eldarion-ajax providing base views and mixins to make hooking up views in your project even easier
Home-page: http://github.com/eldarion/django-eldarion-ajax/
Author: Patrick Altman
Author-email: paltman@eldarion.com
License: MIT
Platform: UNKNOWN
Classifier: Development Status :: 4 - Beta
Classifier: Environment :: Web Environment
Classifier: Framework :: Django
Classifier: Intended Audience :: Developers
Classifier: License :: OSI Approved :: MIT License
Classifier: Operating System :: OS Independent
Classifier: Programming Language :: Python
Classifier: Programming Language :: Python :: 2
Classifier: Programming Language :: Python :: 3
Classifier: Topic :: Software Development :: Libraries :: Python Modules
